gui/__init__.py
gui/app.py
edgebridge-0.1.0.dist-info/METADATA
edgebridge-0.1.0.dist-info/WHEEL
edgebridge-0.1.0.dist-info/top_level.txt
edgebridge-0.1.0.dist-info/RECORD
